[
    {
        "name": "Joe Waldron",
        "major": "Computer Science",
        "graduationYear": 2026,
        "isOfficer": true,
        "title": "President",
        "pfp": "",
        "uaNetId": "jaw368"
    },
    {
        "name": "Riley Spires",
        "major": "Computer Science",
        "graduationYear": 2026,
        "isOfficer": true,
        "title": "Vice President",
        "pfp": "",
        "uaNetId": "rjs243"
    },
    {
        "name": "Brooklyn Rodgers",
        "major": "Computer Science",
        "graduationYear": 2026,
        "isOfficer": true,
        "title": "Treasurer",
        "pfp": "",
        "uaNetId": "bbr12"
    },
    {
        "name": "Lucas Ergh",
        "major": "Computer Engineering",
        "graduationYear": 2026,
        "isOfficer": true,
        "title": "Project Manager",
        "pfp": "",
        "uaNetId": "le45"
    },
    {
        "name": "Nathan Manson",
        "major": "Computer Science",
        "graduationYear": 2026,
        "isOfficer": true,
        "title": "Project Manager",
        "pfp": "",
        "uaNetId": "nam149"
    },
    {
        "name": "Ahmed Kheiri",
        "major": "Computer Science",
        "graduationYear": 2026,
        "isOfficer": true,
        "title": "Outreach Coordinator",
        "pfp": "",
        "uaNetId": "ak535"
    },
    {
        "name": "Jack Thorp",
        "major": "Computer Science",
        "graduationYear": 2026,
        "isOfficer": true,
        "title": "Tech Lead",
        "pfp": "",
        "uaNetId": "jjt87"
    },
    {
        "name": "Drew Corliss",
        "major": "Computer Science",
        "graduationYear": 2026,
        "isOfficer": false,
        "title": "Member",
        "pfp": "",
        "uaNetId": "dmc191"
    },
    {
        "name": "William Aey",
        "major": "Computer Science",
        "graduationYear": 2026,
        "isOfficer": false,
        "title": "Member",
        "pfp": "",
        "uaNetId": "wba6"
    },
    {
        "name": "Bruno Defreitas",
        "major": "Computer Science",
        "graduationYear": 2026,
        "isOfficer": false,
        "title": "Member",
        "pfp": "",
        "uaNetId": "bdd38"
    }
]